async_object/__init__.py
async_object/py.typed
async_object/contrib/__init__.py
async_object/contrib/mypy/__init__.py
async_object/contrib/mypy/plugin.py
async_object-2.0.0.dist-info/METADATA
async_object-2.0.0.dist-info/WHEEL
async_object-2.0.0.dist-info/licenses/LICENSE
async_object-2.0.0.dist-info/RECORD
