Metadata-Version: 2.1
Name: async-object
Version: 2.0.0
Summary: async-object let you write classes with async def __init__
Project-URL: Homepage, https://github.com/francis-clairicia/async-object
Author-email: FrankySnow9 <clairicia.rcj.francis@gmail.com>
License-File: LICENSE
Keywords: async,asyncio,init
Classifier: Development Status :: 5 - Production/Stable
Classifier: Intended Audience :: Developers
Classifier: License :: OSI Approved :: MIT License
Classifier: Programming Language :: Python
Classifier: Programming Language :: Python :: 3
Classifier: Programming Language :: Python :: 3 :: Only
Classifier: Programming Language :: Python :: 3.9
Classifier: Programming Language :: Python :: 3.10
Classifier: Programming Language :: Python :: 3.11
Classifier: Programming Language :: Python :: 3.12
Classifier: Topic :: Software Development :: Libraries :: Python Modules
Classifier: Typing :: Typed
Requires-Python: >=3.9
Provides-Extra: mypy
Requires-Dist: mypy>=1.8.0; extra == 'mypy'
